Workbook

Sheet 术语表
A1: 序号 | B1: 术语词条 | C1: 术语英文 | D1: 派生词 | E1: 术语定义 | F1: 术语条目编号 | G1: 同义词/简化词 | H1: 缩略语 | I1: 符号 | J1: 来源 | K1: 注 | L1: 性质 | M1: 体系序号 | N1: 标准号 | O1: 标准名称 | Q1: 标准所属专业 | R1: 一级条标题 | S1: 二级条标题 | T1: 三级条标题 | U1: 是否在技术要素中提及 | V1: 术语字数
A2: 1 | B2: 油田化学 | C2: oilfield chemistry | E2: 利用化学方法研究解决油气田勘探开发作业过程中全生命周期化学问题的学科。 | F2: 3.1 | M2: =VLOOKUP(N2,[1]储层改造标准目录!$A:$B,2,0) -> 1 | N2: SY/T 5510-2021 | O2: 油田化学常用术语 | Q2: 油田化学剂及材料 | R2: 通用 | U2: {=SUM(LEN([2]正文!$F:$F)-LEN(SUBSTITUTE([2]正文!$F:$F,B2,"")))/LEN(B2)} -> 1 | V2: =LEN(B2) -> 4
A3: 2 | B3: 油田化学剂/材料 | C3: oilfield chemicals/materials | D3: # | E3: 钻井完井、压裂酸化、采油采气、提高采收率、油气水处理及集输等过程中，用化学方法解决问题所涉及的化学剂/材料。 | F3: 3.2 | G3: 油田化学剂、油田化学材料 | M3: =VLOOKUP(N3,[1]储层改造标准目录!$A:$B,2,0) -> 1 | N3: SY/T 5510-2021 | O3: 油田化学常用术语 | Q3: 油田化学剂及材料 | R3: 通用 | U3: {=SUM(LEN([2]正文!$F:$F)-LEN(SUBSTITUTE([2]正文!$F:$F,B3,"")))/LEN(B3)} -> 0 | V3: =LEN(B3) -> 8
B4: 油田化学剂 | C4: oilfield chemicals | D4: * | F4: 3.2-1 | G4: 油田化学材料 | M4: =VLOOKUP(N4,[1]储层改造标准目录!$A:$B,2,0) -> 1 | N4: SY/T 5510-2021 | O4: 油田化学常用术语 | Q4: 油田化学剂及材料 | R4: 通用 | U4: {=SUM(LEN([2]正文!$F:$F)-LEN(SUBSTITUTE([2]正文!$F:$F,B4,"")))/LEN(B4)} -> 1 | V4: =LEN(B4) -> 5
B5: 油田化学材料 | C5: oilfield materials | D5: * | F5: 3.2-2 | G5: 油田化学剂 | M5: =VLOOKUP(N5,[1]储层改造标准目录!$A:$B,2,0) -> 1 | N5: SY/T 5510-2021 | O5: 油田化学常用术语 | Q5: 油田化学剂及材料 | R5: 通用 | U5: {=SUM(LEN([2]正文!$F:$F)-LEN(SUBSTITUTE([2]正文!$F:$F,B5,"")))/LEN(B5)} -> 0 | V5: =LEN(B5) -> 6
A6: 3 | B6: 表面活性剂 | C6: surfactant | E6: 分子由亲水基团和亲油基团组成，能显著降低表/界面张力的化学剂。 | F6: 3.3 | M6: =VLOOKUP(N6,[1]储层改造标准目录!$A:$B,2,0) -> 1 | N6: SY/T 5510-2021 | O6: 油田化学常用术语 | Q6: 油田化学剂及材料 | R6: 通用 | U6: {=SUM(LEN([2]正文!$F:$F)-LEN(SUBSTITUTE([2]正文!$F:$F,B6,"")))/LEN(B6)} -> 56 | V6: =LEN(B6) -> 5
A7: 4 | B7: 聚合物 | C7: polymer | E7: 由重复结构单元组成的高分子化合物。 | F7: 3.4 | M7: =VLOOKUP(N7,[1]储层改造标准目录!$A:$B,2,0) -> 1 | N7: SY/T 5510-2021 | O7: 油田化学常用术语 | Q7: 油田化学剂及材料 | R7: 通用 | U7: {=SUM(LEN([2]正文!$F:$F)-LEN(SUBSTITUTE([2]正文!$F:$F,B7,"")))/LEN(B7)} -> 31 | V7: =LEN(B7) -> 3
A8: 5 | B8: 纳米材料 | C8: nanometer material | E8: 线度小于100nm的材料。 | F8: 3.5 | M8: =VLOOKUP(N8,[1]储层改造标准目录!$A:$B,2,0) -> 1 | N8: SY/T 5510-2021 | O8: 油田化学常用术语 | Q8: 油田化学剂及材料 | R8: 通用 | U8: {=SUM(LEN([2]正文!$F:$F)-LEN(SUBSTITUTE([2]正文!$F:$F,B8,"")))/LEN(B8)} -> 0 | V8: =LEN(B8) -> 4
A9: 6 | B9: 化学改性 | C9: chemical modification | E9: 用化学方法改变物质的物理化学性质。 | F9: 3.6 | M9: =VLOOKUP(N9,[1]储层改造标准目录!$A:$B,2,0) -> 1 | N9: SY/T 5510-2021 | O9: 油田化学常用术语 | Q9: 油田化学剂及材料 | R9: 通用 | U9: {=SUM(LEN([2]正文!$F:$F)-LEN(SUBSTITUTE([2]正文!$F:$F,B9,"")))/LEN(B9)} -> 0 | V9: =LEN(B9) -> 4
A10: 7 | B10: 配伍性（相容性） | C10: compatibility | D10: # | E10: 工作液体系中各成分间或体系与环境间不发生影响其使用性能的化学和物理变化的性质。 | F10: 3.7 | M10: =VLOOKUP(N10,[1]储层改造标准目录!$A:$B,2,0) -> 1 | N10: SY/T 5510-2021 | O10: 油田化学常用术语 | Q10: 油田化学剂及材料 | R10: 通用 | U10: {=SUM(LEN([2]正文!$F:$F)-LEN(SUBSTITUTE([2]正文!$F:$F,B10,"")))/LEN(B10)} -> 0 | V10: =LEN(B10) -> 8
B11: 配伍性 | D11: * | F11: 3.7-1 | M11: =VLOOKUP(N11,[1]储层改造标准目录!$A:$B,2,0) -> 1 | N11: SY/T 5510-2021 | O11: 油田化学常用术语 | Q11: 油田化学剂及材料 | R11: 通用 | U11: {=SUM(LEN([2]正文!$F:$F)-LEN(SUBSTITUTE([2]正文!$F:$F,B11,"")))/LEN(B11)} -> 76 | V11: =LEN(B11) -> 3
B12: 相容性 | D12: * | F12: 3.7-2 | M12: =VLOOKUP(N12,[1]储层改造标准目录!$A:$B,2,0) -> 1 | N12: SY/T 5510-2021 | O12: 油田化学常用术语 | Q12: 油田化学剂及材料 | R12: 通用 | U12: {=SUM(LEN([2]正文!$F:$F)-LEN(SUBSTITUTE([2]正文!$F:$F,B12,"")))/LEN(B12)} -> 1 | V12: =LEN(B12) -> 3
A13: 8 | B13: 协同效应 | C13: synergism | E13: 两种或两种以上化学剂复配使用，其效果优于同条件下化学剂单独使用效果简单加和的效应。 | F13: 3.8 | M13: =VLOOKUP(N13,[1]储层改造标准目录!$A:$B,2,0) -> 1 | N13: SY/T 5510-2021 | O13: 油田化学常用术语 | Q13: 油田化学剂及材料 | R13: 通用 | U13: {=SUM(LEN([2]正文!$F:$F)-LEN(SUBSTITUTE([2]正文!$F:$F,B13,"")))/LEN(B13)} -> 0 | V13: =LEN(B13) -> 4
A14: 9 | B14: 稳定性 | C14: stability | E14: 油田化学剂或工作液体系在使用环境条件下保持其原有性质的能力。 | F14: 3.9 | M14: =VLOOKUP(N14,[1]储层改造标准目录!$A:$B,2,0) -> 1 | N14: SY/T 5510-2021 | O14: 油田化学常用术语 | Q14: 油田化学剂及材料 | R14: 通用 | U14: {=SUM(LEN([2]正文!$F:$F)-LEN(SUBSTITUTE([2]正文!$F:$F,B14,"")))/LEN(B14)} -> 33 | V14: =LEN(B14) -> 3
A15: 10 | B15: 流变性 | C15: rheology | E15: 在外力作用下化学剂/工作液的流动和形变性质。 | F15: 3.10 | M15: =VLOOKUP(N15,[1]储层改造标准目录!$A:$B,2,0) -> 1 | N15: SY/T 5510-2021 | O15: 油田化学常用术语 | Q15: 油田化学剂及材料 | R15: 通用 | U15: {=SUM(LEN([2]正文!$F:$F)-LEN(SUBSTITUTE([2]正文!$F:$F,B15,"")))/LEN(B15)} -> 4 | V15: =LEN(B15) -> 3
A16: 11 | B16: 黏弹性 | C16: viscoelasticity | E16: 在外力作用下材料/工作液表现出黏性和弹性的双重性质。 | F16: 3.11 | M16: =VLOOKUP(N16,[1]储层改造标准目录!$A:$B,2,0) -> 1 | N16: SY/T 5510-2021 | O16: 油田化学常用术语 | Q16: 油田化学剂及材料 | R16: 通用 | U16: {=SUM(LEN([2]正文!$F:$F)-LEN(SUBSTITUTE([2]正文!$F:$F,B16,"")))/LEN(B16)} -> 29 | V16: =LEN(B16) -> 3
A17: 12 | B17: 剪切稀性 | C17: shear thinming behavior | E17: 化学剂溶液/工作液的表观黏度随剪切速率增加而降低的特性。 | F17: 3.12 | M17: =VLOOKUP(N17,[1]储层改造标准目录!$A:$B,2,0) -> 1 | N17: SY/T 5510-2021 | O17: 油田化学常用术语 | Q17: 油田化学剂及材料 | R17: 通用 | U17: {=SUM(LEN([2]正文!$F:$F)-LEN(SUBSTITUTE([2]正文!$F:$F,B17,"")))/LEN(B17)} -> 0 | V17: =LEN(B17) -> 4
A18: 13 | B18: 交联 | C18: crosslinking | E18: 聚合物分子通过化学反应形成网状结构的过程。 | F18: 3.13 | M18: =VLOOKUP(N18,[1]储层改造标准目录!$A:$B,2,0) -> 1 | N18: SY/T 5510-2021 | O18: 油田化学常用术语 | Q18: 油田化学剂及材料 | R18: 通用 | U18: {=SUM(LEN([2]正文!$F:$F)-LEN(SUBSTITUTE([2]正文!$F:$F,B18,"")))/LEN(B18)} -> 154 | V18: =LEN(B18) -> 2
A19: 14 | B19: 凝（冻）胶 | C19: gel | D19: # | E19: 溶液在一定条件下通过物理或化学作用互相连接形成网状结构的体系。 | F19: 3.14 | M19: =VLOOKUP(N19,[1]储层改造标准目录!$A:$B,2,0) -> 1 | N19: SY/T 5510-2021 | O19: 油田化学常用术语 | Q19: 油田化学剂及材料 | R19: 通用 | U19: {=SUM(LEN([2]正文!$F:$F)-LEN(SUBSTITUTE([2]正文!$F:$F,B19,"")))/LEN(B19)} -> 0 | V19: =LEN(B19) -> 5
B20: 凝胶 | D20: * | F20: 3.14-1 | M20: =VLOOKUP(N20,[1]储层改造标准目录!$A:$B,2,0) -> 1 | N20: SY/T 5510-2021 | O20: 油田化学常用术语 | Q20: 油田化学剂及材料 | R20: 通用 | U20: {=SUM(LEN([2]正文!$F:$F)-LEN(SUBSTITUTE([2]正文!$F:$F,B20,"")))/LEN(B20)} -> 0 | V20: =LEN(B20) -> 2
B21: 冻胶 | D21: * | F21: 3.14-2 | M21: =VLOOKUP(N21,[1]储层改造标准目录!$A:$B,2,0) -> 1 | N21: SY/T 5510-2021 | O21: 油田化学常用术语 | Q21: 油田化学剂及材料 | R21: 通用 | U21: {=SUM(LEN([2]正文!$F:$F)-LEN(SUBSTITUTE([2]正文!$F:$F,B21,"")))/LEN(B21)} -> 126 | V21: =LEN(B21) -> 2
A22: 15 | B22: 破胶 | C22: gel break | E22: 凝/冻胶等体系的网状结构被破坏，体系黏度大幅度降低的过程。 | F22: 3.15 | M22: =VLOOKUP(N22,[1]储层改造标准目录!$A:$B,2,0) -> 1 | N22: SY/T 5510-2021 | O22: 油田化学常用术语 | Q22: 油田化学剂及材料 | R22: 通用 | U22: {=SUM(LEN([2]正文!$F:$F)-LEN(SUBSTITUTE([2]正文!$F:$F,B22,"")))/LEN(B22)} -> 224 | V22: =LEN(B22) -> 2
A23: 16 | B23: 降解 | C23: degradation | E23: 在物理、化学或生物因素作用下，化学剂及材料发生断链/分解引发其性能显著变化的过程。 | F23: 3.16 | M23: =VLOOKUP(N23,[1]储层改造标准目录!$A:$B,2,0) -> 1 | N23: SY/T 5510-2021 | O23: 油田化学常用术语 | Q23: 油田化学剂及材料 | R23: 通用 | U23: {=SUM(LEN([2]正文!$F:$F)-LEN(SUBSTITUTE([2]正文!$F:$F,B23,"")))/LEN(B23)} -> 22 | V23: =LEN(B23) -> 2
A24: 17 | B24: 乳化 | C24: emulsification | E24: 互不相溶的两液相中的一相以微小液滴分散在另一液相的化学现象。 | F24: 3.17 | M24: =VLOOKUP(N24,[1]储层改造标准目录!$A:$B,2,0) -> 1 | N24: SY/T 5510-2021 | O24: 油田化学常用术语 | Q24: 油田化学剂及材料 | R24: 通用 | U24: {=SUM(LEN([2]正文!$F:$F)-LEN(SUBSTITUTE([2]正文!$F:$F,B24,"")))/LEN(B24)} -> 32 | V24: =LEN(B24) -> 2
A25: 18 | B25: 破乳 | C25: demulsification | E25: 使乳状液两相分离的现象。 | F25: 3.18 | M25: =VLOOKUP(N25,[1]储层改造标准目录!$A:$B,2,0) -> 1 | N25: SY/T 5510-2021 | O25: 油田化学常用术语 | Q25: 油田化学剂及材料 | R25: 通用 | U25: {=SUM(LEN([2]正文!$F:$F)-LEN(SUBSTITUTE([2]正文!$F:$F,B25,"")))/LEN(B25)} -> 22 | V25: =LEN(B25) -> 2
A26: 19 | B26: 吸附 | C26: adsorption | E26: 化学剂在相界面上富集的现象。 | F26: 3.19 | M26: =VLOOKUP(N26,[1]储层改造标准目录!$A:$B,2,0) -> 1 | N26: SY/T 5510-2021 | O26: 油田化学常用术语 | Q26: 油田化学剂及材料 | R26: 通用 | U26: {=SUM(LEN([2]正文!$F:$F)-LEN(SUBSTITUTE([2]正文!$F:$F,B26,"")))/LEN(B26)} -> 13 | V26: =LEN(B26) -> 2
A27: 20 | B27: 润湿 | C27: wetting | E27: 液体在与固体接触时，沿固体表面扩展的现象。 | F27: 3.20 | M27: =VLOOKUP(N27,[1]储层改造标准目录!$A:$B,2,0) -> 1 | N27: SY/T 5510-2021 | O27: 油田化学常用术语 | Q27: 油田化学剂及材料 | R27: 通用 | U27: {=SUM(LEN([2]正文!$F:$F)-LEN(SUBSTITUTE([2]正文!$F:$F,B27,"")))/LEN(B27)} -> 48 | V27: =LEN(B27) -> 2
A28: 21 | B28: 润湿反转 | C28: wettability alteration | E28: 岩石表面在一定条件下亲水性和亲油性互相转化的现象。 | F28: 3.21 | M28: =VLOOKUP(N28,[1]储层改造标准目录!$A:$B,2,0) -> 1 | N28: SY/T 5510-2021 | O28: 油田化学常用术语 | Q28: 油田化学剂及材料 | R28: 通用 | U28: {=SUM(LEN([2]正文!$F:$F)-LEN(SUBSTITUTE([2]正文!$F:$F,B28,"")))/LEN(B28)} -> 0 | V28: =LEN(B28) -> 4
A29: 22 | B29: 分散 | C29: dispersion | E29: 不相溶固体/液体/气体以微小颗粒分布于溶液中的过程。 | F29: 3.22 | M29: =VLOOKUP(N29,[1]储层改造标准目录!$A:$B,2,0) -> 1 | N29: SY/T 5510-2021 | O29: 油田化学常用术语 | Q29: 油田化学剂及材料 | R29: 通用 | U29: {=SUM(LEN([2]正文!$F:$F)-LEN(SUBSTITUTE([2]正文!$F:$F,B29,"")))/LEN(B29)} -> 22 | V29: =LEN(B29) -> 2
A30: 23 | B30: 发泡 | C30: foaming | E30: 固体或液体中形成气泡的过程。 | F30: 3.23 | M30: =VLOOKUP(N30,[1]储层改造标准目录!$A:$B,2,0) -> 1 | N30: SY/T 5510-2021 | O30: 油田化学常用术语 | Q30: 油田化学剂及材料 | R30: 通用 | U30: {=SUM(LEN([2]正文!$F:$F)-LEN(SUBSTITUTE([2]正文!$F:$F,B30,"")))/LEN(B30)} -> 0 | V30: =LEN(B30) -> 2
A31: 24 | B31: 消泡 | C31: antifoam | E31: 泡沫逐渐减少或消失的过程。 | F31: 3.24 | M31: =VLOOKUP(N31,[1]储层改造标准目录!$A:$B,2,0) -> 1 | N31: SY/T 5510-2021 | O31: 油田化学常用术语 | Q31: 油田化学剂及材料 | R31: 通用 | U31: {=SUM(LEN([2]正文!$F:$F)-LEN(SUBSTITUTE([2]正文!$F:$F,B31,"")))/LEN(B31)} -> 3 | V31: =LEN(B31) -> 2
A32: 25 | B32: 絮凝 | C32: flocculate | E32: 液体中悬浮微粒聚结成絮状物的过程。 | F32: 3.25 | M32: =VLOOKUP(N32,[1]储层改造标准目录!$A:$B,2,0) -> 1 | N32: SY/T 5510-2021 | O32: 油田化学常用术语 | Q32: 油田化学剂及材料 | R32: 通用 | U32: {=SUM(LEN([2]正文!$F:$F)-LEN(SUBSTITUTE([2]正文!$F:$F,B32,"")))/LEN(B32)} -> 14 | V32: =LEN(B32) -> 2
A33: 26 | B33: 缓蚀 | C33: inhibit corrosion | E33: 抑制或延缓金属等材料被腐蚀的过程。 | F33: 3.26 | M33: =VLOOKUP(N33,[1]储层改造标准目录!$A:$B,2,0) -> 1 | N33: SY/T 5510-2021 | O33: 油田化学常用术语 | Q33: 油田化学剂及材料 | R33: 通用 | U33: {=SUM(LEN([2]正文!$F:$F)-LEN(SUBSTITUTE([2]正文!$F:$F,B33,"")))/LEN(B33)} -> 46 | V33: =LEN(B33) -> 2
A34: 27 | B34: 防垢 | C34: scale inhibit | E34: 防止或延缓溶液中结垢的过程。 | F34: 3.27 | M34: =VLOOKUP(N34,[1]储层改造标准目录!$A:$B,2,0) -> 1 | N34: SY/T 5510-2021 | O34: 油田化学常用术语 | Q34: 油田化学剂及材料 | R34: 通用 | U34: {=SUM(LEN([2]正文!$F:$F)-LEN(SUBSTITUTE([2]正文!$F:$F,B34,"")))/LEN(B34)} -> 6 | V34: =LEN(B34) -> 2
A35: 28 | B35: 除垢 | C35: scale removal | E35: 消除有机垢、无机垢的过程。 | F35: 3.28 | M35: =VLOOKUP(N35,[1]储层改造标准目录!$A:$B,2,0) -> 1 | N35: SY/T 5510-2021 | O35: 油田化学常用术语 | Q35: 油田化学剂及材料 | R35: 通用 | U35: {=SUM(LEN([2]正文!$F:$F)-LEN(SUBSTITUTE([2]正文!$F:$F,B35,"")))/LEN(B35)} -> 0 | V35: =LEN(B35) -> 2
A36: 29 | B36: 杀菌 | C36: sterllize | E36: 抑制或杀灭溶液中的微生物的方法。 | F36: 3.29 | M36: =VLOOKUP(N36,[1]储层改造标准目录!$A:$B,2,0) -> 1 | N36: SY/T 5510-2021 | O36: 油田化学常用术语 | Q36: 油田化学剂及材料 | R36: 通用 | U36: {=SUM(LEN([2]正文!$F:$F)-LEN(SUBSTITUTE([2]正文!$F:$F,B36,"")))/LEN(B36)} -> 34 | V36: =LEN(B36) -> 2
A37: 30 | B37: 除气 | C37: deaerate/degas | E37: 除掉溶液中所溶解的氧气、二氧化碳及硫化氢等气体的过程。 | F37: 3.30 | M37: =VLOOKUP(N37,[1]储层改造标准目录!$A:$B,2,0) -> 1 | N37: SY/T 5510-2021 | O37: 油田化学常用术语 | Q37: 油田化学剂及材料 | R37: 通用 | U37: {=SUM(LEN([2]正文!$F:$F)-LEN(SUBSTITUTE([2]正文!$F:$F,B37,"")))/LEN(B37)} -> 0 | V37: =LEN(B37) -> 2
A38: 31 | B38: 解堵 | C38: blocking remove | E38: 以物理化学方法解除井筒及油藏堵塞的过程。 | F38: 3.31 | M38: =VLOOKUP(N38,[1]储层改造标准目录!$A:$B,2,0) -> 1 | N38: SY/T 5510-2021 | O38: 油田化学常用术语 | Q38: 油田化学剂及材料 | R38: 通用 | U38: {=SUM(LEN([2]正文!$F:$F)-LEN(SUBSTITUTE([2]正文!$F:$F,B38,"")))/LEN(B38)} -> 41 | V38: =LEN(B38) -> 2
... A41: 34 | B41: 表面张力 | C41: surface tension | E41: 气体与液体或固体接触时引起自动收缩力。 | F41: 3.34 | M41: =VLOOKUP(N41,[1]储层改造标准目录!$A:$B,2,0) -> 1 | N41: SY/T 5510-2021 | O41: 油田化学常用术语 | Q41: 油田化学剂及材料 | R41: 通用 | U41: {=SUM(LEN([2]正文!$F:$F)-LEN(SUBSTITUTE([2]正文!$F:$F,B41,"")))/LEN(B41)} -> 65 | V41: =LEN(B41) -> 4
A42: 35 | B42: 亲水亲油平衡值 | C42: hydrophile-lipophile balance value （HLB） | E42: 表征表面活性剂的亲水亲油能力关系的数值。 | F42: 3.35 | H42: =MID(C42,FIND("（",C42)+1,(FIND("）",C42)-FIND("（",C42)-1)) -> HLB | M42: =VLOOKUP(N42,[1]储层改造标准目录!$A:$B,2,0) -> 1 | N42: SY/T 5510-2021 | O42: 油田化学常用术语 | Q42: 油田化学剂及材料 | R42: 通用 | U42: {=SUM(LEN([2]正文!$F:$F)-LEN(SUBSTITUTE([2]正文!$F:$F,B42,"")))/LEN(B42)} -> 0 | V42: =LEN(B42) -> 7
A43: 36 | B43: 临界胶束浓度 | C43: eritleal mlcelle concentratlon （CMC） | E43: 表面活性剂在溶液中形成胶束并使界面性质发生突变时的浓度。 | F43: 3.36 | H43: =MID(C43,FIND("（",C43)+1,(FIND("）",C43)-FIND("（",C43)-1)) -> CMC | M43: =VLOOKUP(N43,[1]储层改造标准目录!$A:$B,2,0) -> 1 | N43: SY/T 5510-2021 | O43: 油田化学常用术语 | Q43: 油田化学剂及材料 | R43: 通用 | U43: {=SUM(LEN([2]正文!$F:$F)-LEN(SUBSTITUTE([2]正文!$F:$F,B43,"")))/LEN(B43)} -> 0 | V43: =LEN(B43) -> 6
A44: 37 | B44: 克拉夫特点 | C44: Krafft point | E44: 离子型表面活性剂溶解度急剧上升的温度。 | F44: 3.37 | M44: =VLOOKUP(N44,[1]储层改造标准目录!$A:$B,2,0) -> 1 | N44: SY/T 5510-2021 | O44: 油田化学常用术语 | Q44: 油田化学剂及材料 | R44: 通用 | U44: {=SUM(LEN([2]正文!$F:$F)-LEN(SUBSTITUTE([2]正文!$F:$F,B44,"")))/LEN(B44)} -> 0 | V44: =LEN(B44) -> 5
A45: 38 | B45: 微乳液 | C45: microemulsion | E45: 由油、水、表面活性剂和电解质等组成的透明或半透明的热力学稳定体系。 | F45: 3.38 | M45: =VLOOKUP(N45,[1]储层改造标准目录!$A:$B,2,0) -> 1 | N45: SY/T 5510-2021 | O45: 油田化学常用术语 | Q45: 油田化学剂及材料 | R45: 通用 | U45: {=SUM(LEN([2]正文!$F:$F)-LEN(SUBSTITUTE([2]正文!$F:$F,B45,"")))/LEN(B45)} -> 0 | V45: =LEN(B45) -> 3
A46: 39 | B46: 浊点 | C46: cloud point | E46: 随温度变化，有机化合物从溶解到析出、溶液由透明变混浊所对应的温度。 | F46: 3.39 | M46: =VLOOKUP(N46,[1]储层改造标准目录!$A:$B,2,0) -> 1 | N46: SY/T 5510-2021 | O46: 油田化学常用术语 | Q46: 油田化学剂及材料 | R46: 通用 | U46: {=SUM(LEN([2]正文!$F:$F)-LEN(SUBSTITUTE([2]正文!$F:$F,B46,"")))/LEN(B46)} -> 5 | V46: =LEN(B46) -> 2
A47: 40 | B47: 液流转向 | C47: divert | E47: 利用各种化学剂（材料）、化学反应使流体在储层中流动阻力增加或封堵，工作液流动方向发生改变的过程。 | F47: 3.40 | M47: =VLOOKUP(N47,[1]储层改造标准目录!$A:$B,2,0) -> 1 | N47: SY/T 5510-2021 | O47: 油田化学常用术语 | Q47: 油田化学剂及材料 | R47: 通用 | U47: {=SUM(LEN([2]正文!$F:$F)-LEN(SUBSTITUTE([2]正文!$F:$F,B47,"")))/LEN(B47)} -> 0 | V47: =LEN(B47) -> 4
A48: 41 | B48: 暂堵 | C48: temporary conformance | E48: 利用化学剂（材料）对炮眼、地层裂缝、孔隙等形成封堵并能通过物理、化学方法解除其封堵的过程。 | F48: 3.41 | M48: =VLOOKUP(N48,[1]储层改造标准目录!$A:$B,2,0) -> 1 | N48: SY/T 5510-2021 | O48: 油田化学常用术语 | Q48: 油田化学剂及材料 | R48: 通用 | U48: {=SUM(LEN([2]正文!$F:$F)-LEN(SUBSTITUTE([2]正文!$F:$F,B48,"")))/LEN(B48)} -> 30 | V48: =LEN(B48) -> 2
A49: 42 | B49: 洗井液 | C49: washing fluid | E49: 冲洗井筒，消除井内原油、沉渣、砂等沉积物的工作流体 | F49: 3.42 | M49: =VLOOKUP(N49,[1]储层改造标准目录!$A:$B,2,0) -> 1 | N49: SY/T 5510-2021 | O49: 油田化学常用术语 | Q49: 油田化学剂及材料 | R49: 通用 | U49: {=SUM(LEN([2]正文!$F:$F)-LEN(SUBSTITUTE([2]正文!$F:$F,B49,"")))/LEN(B49)} -> 14 | V49: =LEN(B49) -> 3
A50: 43 | B50: 储保护 | C50: reservoir protection | E50: 防止和减轻储层渗透率显著下降的过程。 | F50: 3.43 | M50: =VLOOKUP(N50,[1]储层改造标准目录!$A:$B,2,0) -> 1 | N50: SY/T 5510-2021 | O50: 油田化学常用术语 | Q50: 油田化学剂及材料 | R50: 通用 | U50: {=SUM(LEN([2]正文!$F:$F)-LEN(SUBSTITUTE([2]正文!$F:$F,B50,"")))/LEN(B50)} -> 0 | V50: =LEN(B50) -> 3
A51: 44 | B51: 水敏 | C51: water sensitivity | E51: 水进入储层后引起黏土水化膨胀、分散运移，导致储层渗透率下降的现象。 | F51: 3.44 | M51: =VLOOKUP(N51,[1]储层改造标准目录!$A:$B,2,0) -> 1 | N51: SY/T 5510-2021 | O51: 油田化学常用术语 | Q51: 油田化学剂及材料 | R51: 通用 | U51: {=SUM(LEN([2]正文!$F:$F)-LEN(SUBSTITUTE([2]正文!$F:$F,B51,"")))/LEN(B51)} -> 2 | V51: =LEN(B51) -> 2
A52: 45 | B52: 碱敏 | C52: alkali sensitivity | E52: 碱性工作液进入储层后导致黏土水化膨胀和分散、黏土矿物生成硅凝胶以及无机离子形成盐垢引起储层渗透率下降的现象。 | F52: 3.45 | M52: =VLOOKUP(N52,[1]储层改造标准目录!$A:$B,2,0) -> 1 | N52: SY/T 5510-2021 | O52: 油田化学常用术语 | Q52: 油田化学剂及材料 | R52: 通用 | U52: {=SUM(LEN([2]正文!$F:$F)-LEN(SUBSTITUTE([2]正文!$F:$F,B52,"")))/LEN(B52)} -> 0 | V52: =LEN(B52) -> 2
A53: 46 | B53: 酸敏 | C53: acid sensitivity | E53: 酸性工作液与储层矿物发生化学反应，生成化学沉淀物和/或矿物微量释放，导致储层渗透率下降的现象。 | F53: 3.46 | M53: =VLOOKUP(N53,[1]储层改造标准目录!$A:$B,2,0) -> 1 | N53: SY/T 5510-2021 | O53: 油田化学常用术语 | Q53: 油田化学剂及材料 | R53: 通用 | U53: {=SUM(LEN([2]正文!$F:$F)-LEN(SUBSTITUTE([2]正文!$F:$F,B53,"")))/LEN(B53)} -> 2 | V53: =LEN(B53) -> 2
A54: 47 | B54: 盐敏 | C54: salt sensitivity | E54: 工作液中盐进入地层，形成沉淀物或大分子聚集，导致储层渗透率下降的现象。 | F54: 3.47 | M54: =VLOOKUP(N54,[1]储层改造标准目录!$A:$B,2,0) -> 1 | N54: SY/T 5510-2021 | O54: 油田化学常用术语 | Q54: 油田化学剂及材料 | R54: 通用 | U54: {=SUM(LEN([2]正文!$F:$F)-LEN(SUBSTITUTE([2]正文!$F:$F,B54,"")))/LEN(B54)} -> 0 | V54: =LEN(B54) -> 2
A55: 48 | B55: 生物毒性 | C55: biotoxicity | E55: 油气口勘探开发污染物与生物接触或进人生物活体体内后，能引起直接或问接损害作用的相对能力。 | F55: 3.48 | M55: =VLOOKUP(N55,[1]储层改造标准目录!$A:$B,2,0) -> 1 | N55: SY/T 5510-2021 | O55: 油田化学常用术语 | Q55: 油田化学剂及材料 | R55: 通用 | U55: {=SUM(LEN([2]正文!$F:$F)-LEN(SUBSTITUTE([2]正文!$F:$F,B55,"")))/LEN(B55)} -> 0 | V55: =LEN(B55) -> 4
A56: 49 | B56: 生物降解性 | C56: biodegradability | E56: 有机物质被土壤，天然水体或废水处理系统中的微生物通过生物代谢作用被转化为简单无机物的性质。[来源：SY/T6787-2010，3.3] | F56: 3.49 | J56: 来源：SY/T6787-2010，3.3 | M56: =VLOOKUP(N56,[1]储层改造标准目录!$A:$B,2,0) -> 1 | N56: SY/T 5510-2021 | O56: 油田化学常用术语 | Q56: 油田化学剂及材料 | R56: 通用 | U56: {=SUM(LEN([2]正文!$F:$F)-LEN(SUBSTITUTE([2]正文!$F:$F,B56,"")))/LEN(B56)} -> 0 | V56: =LEN(B56) -> 5
A57: 50 | B57: 生物修复 | C57: bioremediation | E57: 利用微生物的代谢作用将有害的有机污染物降解为无害的无机物或其他物质的过程。 | F57: 3.50 | M57: =VLOOKUP(N57,[1]储层改造标准目录!$A:$B,2,0) -> 1 | N57: SY/T 5510-2021 | O57: 油田化学常用术语 | Q57: 油田化学剂及材料 | R57: 通用 | U57: {=SUM(LEN([2]正文!$F:$F)-LEN(SUBSTITUTE([2]正文!$F:$F,B57,"")))/LEN(B57)} -> 0 | V57: =LEN(B57) -> 4
A58: 51 | B58: 生物需氧量 | C58: biological oxygen demand（BOD） | E58: 有氧条件下，好氧微生物氧化分解有机物所消耗的游离氧的数量。 | F58: 3.51 | H58: =MID(C58,FIND("（",C58)+1,(FIND("）",C58)-FIND("（",C58)-1)) -> BOD | M58: =VLOOKUP(N58,[1]储层改造标准目录!$A:$B,2,0) -> 1 | N58: SY/T 5510-2021 | O58: 油田化学常用术语 | Q58: 油田化学剂及材料 | R58: 通用 | U58: {=SUM(LEN([2]正文!$F:$F)-LEN(SUBSTITUTE([2]正文!$F:$F,B58,"")))/LEN(B58)} -> 0 | V58: =LEN(B58) -> 5
A59: 52 | B59: 化学需量 | C59: chemical oxygen demand（COD） | E59: 在一定条件下，用重铬酸钾或高锰酸钾氧化处理有机物时所消耗的氧化剂的量，以氧的浓度表示。 | F59: 3.52 | H59: =MID(C59,FIND("（",C59)+1,(FIND("）",C59)-FIND("（",C59)-1)) -> COD | M59: =VLOOKUP(N59,[1]储层改造标准目录!$A:$B,2,0) -> 1 | N59: SY/T 5510-2021 | O59: 油田化学常用术语 | Q59: 油田化学剂及材料 | R59: 通用 | U59: {=SUM(LEN([2]正文!$F:$F)-LEN(SUBSTITUTE([2]正文!$F:$F,B59,"")))/LEN(B59)} -> 0 | V59: =LEN(B59) -> 4
A60: 53 | B60: 钻井液 | C60: drilling fluid | E60: 钻井过程中用以满足钻井工作需要的各种循环流体。[来源：GB/T28911-2012，11.1.1，有修改] | F60: 4.1.1 | J60: 来源：GB/T28911-2012，11.1.1，有修改 | M60: =VLOOKUP(N60,[1]储层改造标准目录!$A:$B,2,0) -> 1 | N60: SY/T 5510-2021 | O60: 油田化学常用术语 | Q60: 油田化学剂及材料 | R60: 钻井完井 | S60: 钻井 | U60: {=SUM(LEN([2]正文!$F:$F)-LEN(SUBSTITUTE([2]正文!$F:$F,B60,"")))/LEN(B60)} -> 72 | V60: =LEN(B60) -> 3
A61: 54 | B61: 水基钻井液 | C61: water-base drilling fluld | E61: 以水作连续相的钻井液。 | F61: 4.1.2 | M61: =VLOOKUP(N61,[1]储层改造标准目录!$A:$B,2,0) -> 1 | N61: SY/T 5510-2021 | O61: 油田化学常用术语 | Q61: 油田化学剂及材料 | R61: 钻井完井 | S61: 钻井 | U61: {=SUM(LEN([2]正文!$F:$F)-LEN(SUBSTITUTE([2]正文!$F:$F,B61,"")))/LEN(B61)} -> 0 | V61: =LEN(B61) -> 5
A62: 55 | B62: 分散钻井液 | C62: dispersed drilling fluid | E62: 通过使用分散剂，以促进钻井液中黏土分散为主的水基钻井液。[来源：GB/T28911-2012，11.1.2.1] | F62: 4.1.3 | J62: 来源：GB/T28911-2012，11.1.2.1 | M62: =VLOOKUP(N62,[1]储层改造标准目录!$A:$B,2,0) -> 1 | N62: SY/T 5510-2021 | O62: 油田化学常用术语 | Q62: 油田化学剂及材料 | R62: 钻井完井 | S62: 钻井 | U62: {=SUM(LEN([2]正文!$F:$F)-LEN(SUBSTITUTE([2]正文!$F:$F,B62,"")))/LEN(B62)} -> 0 | V62: =LEN(B62) -> 5
A63: 56 | B63: 不分散钻井液 | C63: non-dispersed drilling fluid | E63: 由水，膨润土、高聚物（选择性絮凝剂）组成，不促进钻井液中黏土分散的水基钻井液。[来源：GB/T28911-2012，11.1.2.2] | F63: 4.1.4 | J63: 来源：GB/T28911-2012，11.1.2.2 | M63: =VLOOKUP(N63,[1]储层改造标准目录!$A:$B,2,0) -> 1 | N63: SY/T 5510-2021 | O63: 油田化学常用术语 | Q63: 油田化学剂及材料 | R63: 钻井完井 | S63: 钻井 | U63: {=SUM(LEN([2]正文!$F:$F)-LEN(SUBSTITUTE([2]正文!$F:$F,B63,"")))/LEN(B63)} -> 0 | V63: =LEN(B63) -> 6
A64: 57 | B64: 钙处理钻井液 | C64: calcium-treated drilling fluid | E64: 经石灰、石膏或氯化钙等处理过的，具有抑制黏土膨胀特性的水基钻井液。[来源：GB/T28911-2012，11.1.2.3，有修改] | F64: 4.1.5 | J64: 来源：GB/T28911-2012，11.1.2.3，有修改 | M64: =VLOOKUP(N64,[1]储层改造标准目录!$A:$B,2,0) -> 1 | N64: SY/T 5510-2021 | O64: 油田化学常用术语 | Q64: 油田化学剂及材料 | R64: 钻井完井 | S64: 钻井 | U64: {=SUM(LEN([2]正文!$F:$F)-LEN(SUBSTITUTE([2]正文!$F:$F,B64,"")))/LEN(B64)} -> 0 | V64: =LEN(B64) -> 6
A65: 58 | B65: 聚合物液 | C65: polymer drilling fluid | E65: 以聚合物为主处理剂的水基钻井液。[来源：GB/T28911-2012，11.1.2.4] | F65: 4.1.6 | J65: 来源：GB/T28911-2012，11.1.2.4 | M65: =VLOOKUP(N65,[1]储层改造标准目录!$A:$B,2,0) -> 1 | N65: SY/T 5510-2021 | O65: 油田化学常用术语 | Q65: 油田化学剂及材料 | R65: 钻井完井 | S65: 钻井 | U65: {=SUM(LEN([2]正文!$F:$F)-LEN(SUBSTITUTE([2]正文!$F:$F,B65,"")))/LEN(B65)} -> 0 | V65: =LEN(B65) -> 4
A66: 59 | B66: 低固相钻井液 | C66: low solids drilling fluid | E66: 低密度的固相体积含量小于4％（体积分数）的水基钻井液。[来源：GB/T28911-2012，11.1.2.5] | F66: 4.1.7 | J66: 来源：GB/T28911-2012，11.1.2.5 | M66: =VLOOKUP(N66,[1]储层改造标准目录!$A:$B,2,0) -> 1 | N66: SY/T 5510-2021 | O66: 油田化学常用术语 | Q66: 油田化学剂及材料 | R66: 钻井完井 | S66: 钻井 | U66: {=SUM(LEN([2]正文!$F:$F)-LEN(SUBSTITUTE([2]正文!$F:$F,B66,"")))/LEN(B66)} -> 0 | V66: =LEN(B66) -> 6
A67: 60 | B67: 无固相钻井液 | C67: solids-free drilling fluid | E67: 不加入膨润土、重品石粉等惰性悬浮固相的钻井液。 | F67: 4.1.8 | M67: =VLOOKUP(N67,[1]储层改造标准目录!$A:$B,2,0) -> 1 | N67: SY/T 5510-2021 | O67: 油田化学常用术语 | Q67: 油田化学剂及材料 | R67: 钻井完井 | S67: 钻井 | U67: {=SUM(LEN([2]正文!$F:$F)-LEN(SUBSTITUTE([2]正文!$F:$F,B67,"")))/LEN(B67)} -> 0 | V67: =LEN(B67) -> 6
A68: 61 | B68: 盐水钻井液 | C68: salt-water drilling fluid | E68: 盐含量不小于4％（质量分数）的水基钻井液。[来源：GB/T28911-2012，11.1.2.7，有修改] | F68: 4.1.9 | J68: 来源：GB/T28911-2012，11.1.2.7，有修改 | M68: =VLOOKUP(N68,[1]储层改造标准目录!$A:$B,2,0) -> 1 | N68: SY/T 5510-2021 | O68: 油田化学常用术语 | Q68: 油田化学剂及材料 | R68: 钻井完井 | S68: 钻井 | U68: {=SUM(LEN([2]正文!$F:$F)-LEN(SUBSTITUTE([2]正文!$F:$F,B68,"")))/LEN(B68)} -> 0 | V68: =LEN(B68) -> 5
A69: 62 | B69: 水包油乳化钻井液 | C69: oil-in-water emulsion driling fluid | E69: 以水为连续相，油为分散相的乳化钻井液。[来源：GB/T28911-2012，11.1.2.10] | F69: 4.1.10 | J69: 来源：GB/T28911-2012，11.1.2.10 | M69: =VLOOKUP(N69,[1]储层改造标准目录!$A:$B,2,0) -> 1 | N69: SY/T 5510-2021 | O69: 油田化学常用术语 | Q69: 油田化学剂及材料 | R69: 钻井完井 | S69: 钻井 | U69: {=SUM(LEN([2]正文!$F:$F)-LEN(SUBSTITUTE([2]正文!$F:$F,B69,"")))/LEN(B69)} -> 0 | V69: =LEN(B69) -> 8
A70: 63 | B70: 合成基钻井液 | C70: synthetic base drilling fluid | E70: 以合成的有机化合物作为连续相的钻井液[来源：GB/T28911-2012，11.1.4] | F70: 4.1.11 | J70: 来源：GB/T28911-2012，11.1.4 | M70: =VLOOKUP(N70,[1]储层改造标准目录!$A:$B,2,0) -> 1 | N70: SY/T 5510-2021 | O70: 油田化学常用术语 | Q70: 油田化学剂及材料 | R70: 钻井完井 | S70: 钻井 | U70: {=SUM(LEN([2]正文!$F:$F)-LEN(SUBSTITUTE([2]正文!$F:$F,B70,"")))/LEN(B70)} -> 0 | V70: =LEN(B70) -> 6
A71: 64 | B71: 油基钻井液 | C71: vil-base drilling fluld | E71: 以油作连续相的钻井液。 | F71: 4.1.12 | M71: =VLOOKUP(N71,[1]储层改造标准目录!$A:$B,2,0) -> 1 | N71: SY/T 5510-2021 | O71: 油田化学常用术语 | Q71: 油田化学剂及材料 | R71: 钻井完井 | S71: 钻井 | U71: {=SUM(LEN([2]正文!$F:$F)-LEN(SUBSTITUTE([2]正文!$F:$F,B71,"")))/LEN(B71)} -> 3 | V71: =LEN(B71) -> 5
A72: 65 | B72: 全油基钻井液 | C72: true oil drilling fluid | E72: 以油为连续相，含水量不超过5％（体积分数）的钻井液。[来源：GB/T28911-2012，11.1.3.1] | F72: 4.1.13 | J72: 来源：GB/T28911-2012，11.1.3.1 | M72: =VLOOKUP(N72,[1]储层改造标准目录!$A:$B,2,0) -> 1 | N72: SY/T 5510-2021 | O72: 油田化学常用术语 | Q72: 油田化学剂及材料 | R72: 钻井完井 | S72: 钻井 | U72: {=SUM(LEN([2]正文!$F:$F)-LEN(SUBSTITUTE([2]正文!$F:$F,B72,"")))/LEN(B72)} -> 0 | V72: =LEN(B72) -> 6
A73: 66 | B73: 油包水乳化钻井液 | C73: water in oil emulsion drilling fuid | E73: 以油为连续相，水作分散相的乳化钻井液。[来源：GB/T28911-2012，11.1.3.2] | F73: 4.1.14 | J73: 来源：GB/T28911-2012，11.1.3.2 | M73: =VLOOKUP(N73,[1]储层改造标准目录!$A:$B,2,0) -> 1 | N73: SY/T 5510-2021 | O73: 油田化学常用术语 | Q73: 油田化学剂及材料 | R73: 钻井完井 | S73: 钻井 | U73: {=SUM(LEN([2]正文!$F:$F)-LEN(SUBSTITUTE([2]正文!$F:$F,B73,"")))/LEN(B73)} -> 0 | V73: =LEN(B73) -> 8
A74: 67 | B74: 气体钻井流体 | C74: gaseous drilling fluid | E74: 用空气、天然气、氮气等气体作为循环介质的钻井流体。[来源：GB/T28911-2012，11.1.5.1] | F74: 4.1.15 | J74: 来源：GB/T28911-2012，11.1.5.1 | M74: =VLOOKUP(N74,[1]储层改造标准目录!$A:$B,2,0) -> 1 | N74: SY/T 5510-2021 | O74: 油田化学常用术语 | Q74: 油田化学剂及材料 | R74: 钻井完井 | S74: 钻井 | U74: {=SUM(LEN([2]正文!$F:$F)-LEN(SUBSTITUTE([2]正文!$F:$F,B74,"")))/LEN(B74)} -> 0 | V74: =LEN(B74) -> 6
A75: 68 | B75: 雾化钻井流体 | C75: mist drilling fluid | E75: 水分散在气体介质中所形成的雾状钻井流体。[来源：GB/T28911-2012，11.1.5.2] | F75: 4.1.16 | J75: 来源：GB/T28911-2012，11.1.5.2 | M75: =VLOOKUP(N75,[1]储层改造标准目录!$A:$B,2,0) -> 1 | N75: SY/T 5510-2021 | O75: 油田化学常用术语 | Q75: 油田化学剂及材料 | R75: 钻井完井 | S75: 钻井 | U75: {=SUM(LEN([2]正文!$F:$F)-LEN(SUBSTITUTE([2]正文!$F:$F,B75,"")))/LEN(B75)} -> 0 | V75: =LEN(B75) -> 6
A76: 69 | B76: 泡沫钻井液 | C76: foam drilling fluid | E76: 将气体分散在加有发泡剂和稳泡剂的液体中形成的钻井流体。[来源：GB/T28911-2012，11.1.2.11，有修改] | F76: 4.1.17 | J76: 来源：GB/T28911-2012，11.1.2.11，有修改 | M76: =VLOOKUP(N76,[1]储层改造标准目录!$A:$B,2,0) -> 1 | N76: SY/T 5510-2021 | O76: 油田化学常用术语 | Q76: 油田化学剂及材料 | R76: 钻井完井 | S76: 钻井 | U76: {=SUM(LEN([2]正文!$F:$F)-LEN(SUBSTITUTE([2]正文!$F:$F,B76,"")))/LEN(B76)} -> 0 | V76: =LEN(B76) -> 5
A77: 70 | B77: 加重钻井液 | C77: weighted drilling fluid | E77: 用加重材料提高了密度的钻井液。[来源：GB/T28911-2012，11.1.6] | F77: 4.1.18 | J77: 来源：GB/T28911-2012，11.1.6 | M77: =VLOOKUP(N77,[1]储层改造标准目录!$A:$B,2,0) -> 1 | N77: SY/T 5510-2021 | O77: 油田化学常用术语 | Q77: 油田化学剂及材料 | R77: 钻井完井 | S77: 钻井 | U77: {=SUM(LEN([2]正文!$F:$F)-LEN(SUBSTITUTE([2]正文!$F:$F,B77,"")))/LEN(B77)} -> 0 | V77: =LEN(B77) -> 5
A78: 71 | B78: 膨润土 | C78: bentonite | E78: 以蒙脱石为主要矿物成分的黏土。 | F78: 4.1.19 | M78: =VLOOKUP(N78,[1]储层改造标准目录!$A:$B,2,0) -> 1 | N78: SY/T 5510-2021 | O78: 油田化学常用术语 | Q78: 油田化学剂及材料 | R78: 钻井完井 | S78: 钻井 | U78: {=SUM(LEN([2]正文!$F:$F)-LEN(SUBSTITUTE([2]正文!$F:$F,B78,"")))/LEN(B78)} -> 52 | V78: =LEN(B78) -> 3
A79: 72 | B79: 有机土 | C79: organic clay | E79: 用表面活性剂处理过、能分散在油中形成亲油胶体并使油基钻井液的黏度和切力升高的黏土。[来源：GB/T28911—2012，11.2.6] | F79: 4.1.20 | J79: 来源：GB/T28911—2012，11.2.6 | M79: =VLOOKUP(N79,[1]储层改造标准目录!$A:$B,2,0) -> 1 | N79: SY/T 5510-2021 | O79: 油田化学常用术语 | Q79: 油田化学剂及材料 | R79: 钻井完井 | S79: 钻井 | U79: {=SUM(LEN([2]正文!$F:$F)-LEN(SUBSTITUTE([2]正文!$F:$F,B79,"")))/LEN(B79)} -> 0 | V79: =LEN(B79) -> 3
A80: 73 | B80: 堵漏材料/堵漏剂 | C80: lost circulation material | D80: # | E80: 能防止或减少钻井液从井筒漏入地层的材料。[来源：GB/T28911-2012，11.2.14] | F80: 4.1.21 | G80: 堵漏材料、堵漏剂 | J80: 来源：GB/T28911-2012，11.2.14 | M80: =VLOOKUP(N80,[1]储层改造标准目录!$A:$B,2,0) -> 1 | N80: SY/T 5510-2021 | O80: 油田化学常用术语 | Q80: 油田化学剂及材料 | R80: 钻井完井 | S80: 钻井 | U80: {=SUM(LEN([2]正文!$F:$F)-LEN(SUBSTITUTE([2]正文!$F:$F,B80,"")))/LEN(B80)} -> 0 | V80: =LEN(B80) -> 8
B81: 堵漏材料 | C81: lost circulation material | D81: * | F81: 4.1.21-1 | G81: 堵漏剂 | J81: 来源：GB/T28911-2012，11.2.14 | M81: =VLOOKUP(N81,[1]储层改造标准目录!$A:$B,2,0) -> 1 | N81: SY/T 5510-2021 | O81: 油田化学常用术语 | Q81: 油田化学剂及材料 | R81: 钻井完井 | S81: 钻井 | U81: {=SUM(LEN([2]正文!$F:$F)-LEN(SUBSTITUTE([2]正文!$F:$F,B81,"")))/LEN(B81)} -> 0 | V81: =LEN(B81) -> 4
B82: 堵漏剂 | C82: lost circulation material | D82: * | F82: 4.1.21-2 | G82: 堵漏材料 | J82: 来源：GB/T28911-2012，11.2.14 | M82: =VLOOKUP(N82,[1]储层改造标准目录!$A:$B,2,0) -> 1 | N82: SY/T 5510-2021 | O82: 油田化学常用术语 | Q82: 油田化学剂及材料 | R82: 钻井完井 | S82: 钻井 | U82: {=SUM(LEN([2]正文!$F:$F)-LEN(SUBSTITUTE([2]正文!$F:$F,B82,"")))/LEN(B82)} -> 0 | V82: =LEN(B82) -> 3
A83: 74 | B83: 加重材料加重剂 | C83: weighting material | E83: 用于提高钻井液密度的材料。[来源：GB/T8423.2-2018，2.8.2.3，有修改」 | F83: 4.1.22 | J83: 来源：GB/T8423.2-2018，2.8.2.3，有修改 | M83: =VLOOKUP(N83,[1]储层改造标准目录!$A:$B,2,0) -> 1 | N83: SY/T 5510-2021 | O83: 油田化学常用术语 | Q83: 油田化学剂及材料 | R83: 钻井完井 | S83: 钻井 | U83: {=SUM(LEN([2]正文!$F:$F)-LEN(SUBSTITUTE([2]正文!$F:$F,B83,"")))/LEN(B83)} -> 0 | V83: =LEN(B83) -> 7
A84: 75 | B84: 钻井液增黏剂 | C84: drllling nuld viscusner | E84: 增加钻井液黏度的化学剂。 | F84: 4.1.23 | M84: =VLOOKUP(N84,[1]储层改造标准目录!$A:$B,2,0) -> 1 | N84: SY/T 5510-2021 | O84: 油田化学常用术语 | Q84: 油田化学剂及材料 | R84: 钻井完井 | S84: 钻井 | U84: {=SUM(LEN([2]正文!$F:$F)-LEN(SUBSTITUTE([2]正文!$F:$F,B84,"")))/LEN(B84)} -> 0 | V84: =LEN(B84) -> 6
A85: 76 | B85: 钻井液提切剂 | C85: drilling fluid rheology modifer | E85: 提高钻井液切力的化学剂。 | F85: 4.1.24 | M85: =VLOOKUP(N85,[1]储层改造标准目录!$A:$B,2,0) -> 1 | N85: SY/T 5510-2021 | O85: 油田化学常用术语 | Q85: 油田化学剂及材料 | R85: 钻井完井 | S85: 钻井 | U85: {=SUM(LEN([2]正文!$F:$F)-LEN(SUBSTITUTE([2]正文!$F:$F,B85,"")))/LEN(B85)} -> 0 | V85: =LEN(B85) -> 6
A86: 77 | B86: 钻井液降黏剂 | C86: drilling fluid thinmer | E86: 降低钻井液黏度和切力的化学剂。 | F86: 4.1.25 | M86: =VLOOKUP(N86,[1]储层改造标准目录!$A:$B,2,0) -> 1 | N86: SY/T 5510-2021 | O86: 油田化学常用术语 | Q86: 油田化学剂及材料 | R86: 钻井完井 | S86: 钻井 | U86: {=SUM(LEN([2]正文!$F:$F)-LEN(SUBSTITUTE([2]正文!$F:$F,B86,"")))/LEN(B86)} -> 0 | V86: =LEN(B86) -> 6
A87: 78 | B87: 钻井液降滤失剂 | C87: drilling fluid filtrate reducer | E87: 降低钻井液滤失量的化学剂。[来源：GB/T8423.2-2018，2.8.2.4] | F87: 4.1.26 | J87: 来源：GB/T8423.2-2018，2.8.2.4 | M87: =VLOOKUP(N87,[1]储层改造标准目录!$A:$B,2,0) -> 1 | N87: SY/T 5510-2021 | O87: 油田化学常用术语 | Q87: 油田化学剂及材料 | R87: 钻井完井 | S87: 钻井 | U87: {=SUM(LEN([2]正文!$F:$F)-LEN(SUBSTITUTE([2]正文!$F:$F,B87,"")))/LEN(B87)} -> 0 | V87: =LEN(B87) -> 7
A88: 79 | B88: 钻井液杀菌剂 | C88: drilling fluid bactericide | E88: 杀灭或抑制钻井液中细菌生长繁殖的化学剂。[来源：GB/T28911-2012，11.2.28] | F88: 4.1.27 | J88: 来源：GB/T28911-2012，11.2.28 | M88: =VLOOKUP(N88,[1]储层改造标准目录!$A:$B,2,0) -> 1 | N88: SY/T 5510-2021 | O88: 油田化学常用术语 | Q88: 油田化学剂及材料 | R88: 钻井完井 | S88: 钻井 | U88: {=SUM(LEN([2]正文!$F:$F)-LEN(SUBSTITUTE([2]正文!$F:$F,B88,"")))/LEN(B88)} -> 0 | V88: =LEN(B88) -> 6
A89: 80 | B89: 钻井液缓蚀剂 | C89: corrosion inhibitor for drilling fluid | E89: 用于减轻或抑制钻并液对设备及管柱腐蚀的处理剂。[来源：GB/T28911-2012，11.2.23] | F89: 4.1.28 | J89: 来源：GB/T28911-2012，11.2.23 | M89: =VLOOKUP(N89,[1]储层改造标准目录!$A:$B,2,0) -> 1 | N89: SY/T 5510-2021 | O89: 油田化学常用术语 | Q89: 油田化学剂及材料 | R89: 钻井完井 | S89: 钻井 | U89: {=SUM(LEN([2]正文!$F:$F)-LEN(SUBSTITUTE([2]正文!$F:$F,B89,"")))/LEN(B89)} -> 0 | V89: =LEN(B89) -> 6
A90: 81 | B90: 钻井液发泡剂 | C90: foaming agent for drilling fluid | E90: 促使钻井液形成稳定泡沫的化学剂。[来源：GB/T28911-2012，11.2.17] | F90: 4.1.29 | J90: 来源：GB/T28911-2012，11.2.17 | M90: =VLOOKUP(N90,[1]储层改造标准目录!$A:$B,2,0) -> 1 | N90: SY/T 5510-2021 | O90: 油田化学常用术语 | Q90: 油田化学剂及材料 | R90: 钻井完井 | S90: 钻井 | U90: {=SUM(LEN([2]正文!$F:$F)-LEN(SUBSTITUTE([2]正文!$F:$F,B90,"")))/LEN(B90)} -> 0 | V90: =LEN(B90) -> 6
A91: 82 | B91: 钻井液消泡剂 | C91: defoamer for drilling fluid | E91: 减少或消除钻井液中泡沫的化学剂。 | F91: 4.1.30 | M91: =VLOOKUP(N91,[1]储层改造标准目录!$A:$B,2,0) -> 1 | N91: SY/T 5510-2021 | O91: 油田化学常用术语 | Q91: 油田化学剂及材料 | R91: 钻井完井 | S91: 钻井 | U91: {=SUM(LEN([2]正文!$F:$F)-LEN(SUBSTITUTE([2]正文!$F:$F,B91,"")))/LEN(B91)} -> 0 | V91: =LEN(B91) -> 6
A92: 83 | B92: 钻井液稳泡剂 | C92: foam stabilizer for drilling fluid | E92: 增强钻井液泡沫稳定性的化学剂。 | F92: 4.1.31 | M92: =VLOOKUP(N92,[1]储层改造标准目录!$A:$B,2,0) -> 1 | N92: SY/T 5510-2021 | O92: 油田化学常用术语 | Q92: 油田化学剂及材料 | R92: 钻井完井 | S92: 钻井 | U92: {=SUM(LEN([2]正文!$F:$F)-LEN(SUBSTITUTE([2]正文!$F:$F,B92,"")))/LEN(B92)} -> 0 | V92: =LEN(B92) -> 6
A93: 84 | B93: 钻井液乳化剂 | C93: drilling fluid emulsifier | E93: 能促使钻井液油水乳化并使乳状液稳定的化学剂。 | F93: 4.1.32 | M93: =VLOOKUP(N93,[1]储层改造标准目录!$A:$B,2,0) -> 1 | N93: SY/T 5510-2021 | O93: 油田化学常用术语 | Q93: 油田化学剂及材料 | R93: 钻井完井 | S93: 钻井 | U93: {=SUM(LEN([2]正文!$F:$F)-LEN(SUBSTITUTE([2]正文!$F:$F,B93,"")))/LEN(B93)} -> 0 | V93: =LEN(B93) -> 6
A94: 85 | B94: 钻井液絮剂 | C94: flocculant for drilling fluid | E94: 能使钻井液中黏土颗粒或劣质固相聚结或絮凝的化学剂。 | F94: 4.1.33 | M94: =VLOOKUP(N94,[1]储层改造标准目录!$A:$B,2,0) -> 1 | N94: SY/T 5510-2021 | O94: 油田化学常用术语 | Q94: 油田化学剂及材料 | R94: 钻井完井 | S94: 钻井 | U94: {=SUM(LEN([2]正文!$F:$F)-LEN(SUBSTITUTE([2]正文!$F:$F,B94,"")))/LEN(B94)} -> 0 | V94: =LEN(B94) -> 5
A95: 86 | B95: 钻井液润滑剂 | C95: lubricant for drilling fluid | E95: 能提高钻井液润滑性能的化学剂。[来源：GB/T28911-2012，11.2.12] | F95: 4.1.34 | J95: 来源：GB/T28911-2012，11.2.12 | M95: =VLOOKUP(N95,[1]储层改造标准目录!$A:$B,2,0) -> 1 | N95: SY/T 5510-2021 | O95: 油田化学常用术语 | Q95: 油田化学剂及材料 | R95: 钻井完井 | S95: 钻井 | U95: {=SUM(LEN([2]正文!$F:$F)-LEN(SUBSTITUTE([2]正文!$F:$F,B95,"")))/LEN(B95)} -> 0 | V95: =LEN(B95) -> 6
A96: 87 | B96: 钻井液pH值控制剂 | C96: pH control agent for drilling fluid | E96: 能控制钻井液酸碱度的化学剂。 | F96: 4.1.35 | M96: =VLOOKUP(N96,[1]储层改造标准目录!$A:$B,2,0) -> 1 | N96: SY/T 5510-2021 | O96: 油田化学常用术语 | Q96: 油田化学剂及材料 | R96: 钻井完井 | S96: 钻井 | U96: {=SUM(LEN([2]正文!$F:$F)-LEN(SUBSTITUTE([2]正文!$F:$F,B96,"")))/LEN(B96)} -> 0 | V96: =LEN(B96) -> 9
A97: 88 | B97: 钻井液除钙剂 | C97: calcium remover for drilling fluid | E97: 能除去钻井液中钙离子的化学剂。 | F97: 4.1.36 | M97: =VLOOKUP(N97,[1]储层改造标准目录!$A:$B,2,0) -> 1 | N97: SY/T 5510-2021 | O97: 油田化学常用术语 | Q97: 油田化学剂及材料 | R97: 钻井完井 | S97: 钻井 | U97: {=SUM(LEN([2]正文!$F:$F)-LEN(SUBSTITUTE([2]正文!$F:$F,B97,"")))/LEN(B97)} -> 0 | V97: =LEN(B97) -> 6
A98: 89 | B98: 钻井液包被剂 | C98: encapsulating agent for drilling fuid | E98: 在钻屑或劣质固相表面发生多点吸附并对其进行包被的大分子处理剂。 | F98: 4.1.37 | M98: =VLOOKUP(N98,[1]储层改造标准目录!$A:$B,2,0) -> 1 | N98: SY/T 5510-2021 | O98: 油田化学常用术语 | Q98: 油田化学剂及材料 | R98: 钻井完井 | S98: 钻井 | U98: {=SUM(LEN([2]正文!$F:$F)-LEN(SUBSTITUTE([2]正文!$F:$F,B98,"")))/LEN(B98)} -> 0 | V98: =LEN(B98) -> 6
A99: 90 | B99: 钻井液防泥包剂 | C99: balling inhibitor for drilling fluid | E99: 防止钻头和钻县泥包的处理剂。[来源：GB/T28911-2012，11.2.21] | F99: 4.1.38 | J99: 来源：GB/T28911-2012，11.2.21 | M99: =VLOOKUP(N99,[1]储层改造标准目录!$A:$B,2,0) -> 1 | N99: SY/T 5510-2021 | O99: 油田化学常用术语 | Q99: 油田化学剂及材料 | R99: 钻井完井 | S99: 钻井 | U99: {=SUM(LEN([2]正文!$F:$F)-LEN(SUBSTITUTE([2]正文!$F:$F,B99,"")))/LEN(B99)} -> 0 | V99: =LEN(B99) -> 7
A100: 91 | B100: 钻井液高温稳定剂 | C100: high temperature stabilizer for drilling fluid | E100: 能提高钻并液高温稳定性的化学剂。 | F100: 4.1.39 | M100: =VLOOKUP(N100,[1]储层改造标准目录!$A:$B,2,0) -> 1 | N100: SY/T 5510-2021 | O100: 油田化学常用术语 | Q100: 油田化学剂及材料 | R100: 钻井完井 | S100: 钻井 | U100: {=SUM(LEN([2]正文!$F:$F)-LEN(SUBSTITUTE([2]正文!$F:$F,B100,"")))/LEN(B100)} -> 0 | V100: =LEN(B100) -> 8
A101: 92 | B101: 钻井液解卡剂 | C101: pipe-freeing-agent for drilling fluid | E101: 通过渗透作用实现压力传递，用于解除黏附卡钻或压差卡钻的化学剂。[来源：GB/T28911-2012，11.2.22] | F101: 4.1.40 | J101: 来源：GB/T28911-2012，11.2.22 | M101: =VLOOKUP(N101,[1]储层改造标准目录!$A:$B,2,0) -> 1 | N101: SY/T 5510-2021 | O101: 油田化学常用术语 | Q101: 油田化学剂及材料 | R101: 钻井完井 | S101: 钻井 | U101: {=SUM(LEN([2]正文!$F:$F)-LEN(SUBSTITUTE([2]正文!$F:$F,B101,"")))/LEN(B101)} -> 0 | V101: =LEN(B101) -> 6
A102: 93 | B102: 钻井液封堵剂 | C102: drilling fluid blocking agent | E102: 能封堵地层孔隙和裂隙，减少钻井液侵入地层的化学剂。 | F102: 4.1.41 | M102: =VLOOKUP(N102,[1]储层改造标准目录!$A:$B,2,0) -> 1 | N102: SY/T 5510-2021 | O102: 油田化学常用术语 | Q102: 油田化学剂及材料 | R102: 钻井完井 | S102: 钻井 | U102: {=SUM(LEN([2]正文!$F:$F)-LEN(SUBSTITUTE([2]正文!$F:$F,B102,"")))/LEN(B102)} -> 0 | V102: =LEN(B102) -> 6
...
